astropy_xarray/__init__.py
astropy_xarray/accessors.py
astropy_xarray/compat.py
astropy_xarray/conversion.py
astropy_xarray/errors.py
astropy_xarray/formatting.py
astropy_xarray/index.py
astropy_xarray/testing.py
astropy_xarray/tests/__init__.py
astropy_xarray/tests/test_accessors.py
astropy_xarray/tests/test_conversion.py
astropy_xarray/tests/test_formatting.py
astropy_xarray/tests/test_index.py
astropy_xarray/tests/test_testing.py
astropy_xarray/tests/utils.py
astropy_xarray-0.1.0.dist-info/licenses/LICENSE
astropy_xarray-0.1.0.dist-info/licenses/NOTICE
astropy_xarray-0.1.0.dist-info/METADATA
astropy_xarray-0.1.0.dist-info/WHEEL
astropy_xarray-0.1.0.dist-info/top_level.txt
astropy_xarray-0.1.0.dist-info/RECORD
