Metadata-Version: 2.4
Name: astropy-xarray
Version: 0.1.0
Summary: Physical units interface to xarray using astropy
Author-email: Tom Nicholas <tomnicholas1@googlemail.com>, Callan Gray <calj.gray@gmail.com>
License: Apache-2
Project-URL: Home, https://github.com/calgray/astropy-xarray
Project-URL: Documentation, https://astropy-xarray.readthedocs.io/en/stable
Classifier: Development Status :: 3 - Alpha
Classifier: Environment :: Console
Classifier: Intended Audience :: Science/Research
Classifier: License :: OSI Approved :: Apache Software License
Classifier: Operating System :: OS Independent
Classifier: Programming Language :: Python
Classifier: Programming Language :: Python :: 3.10
Classifier: Programming Language :: Python :: 3.11
Classifier: Programming Language :: Python :: 3.12
Classifier: Topic :: Scientific/Engineering
Requires-Python: >=3.10
License-File: LICENSE
License-File: NOTICE
Requires-Dist: numpy>=1.23
Requires-Dist: xarray>=2022.06.0
Requires-Dist: astropy>=5.0.0
Provides-Extra: test
Requires-Dist: pytest>=8.0; extra == "test"
Provides-Extra: docs
Requires-Dist: sphinx>=8.0; extra == "docs"
Requires-Dist: sphinx_auto_summary_accessors; extra == "docs"
Requires-Dist: nbsphinx; extra == "docs"
Requires-Dist: sphinx_rtd_theme; extra == "docs"
Dynamic: license-file
